akitchensyncio/__init__.py
akitchensyncio-0.1.1.dist-info/DESCRIPTION.rst
akitchensyncio-0.1.1.dist-info/METADATA
akitchensyncio-0.1.1.dist-info/RECORD
akitchensyncio-0.1.1.dist-info/WHEEL
akitchensyncio-0.1.1.dist-info/metadata.json
akitchensyncio-0.1.1.dist-info/top_level.txt
