Metadata-Version: 2.0
Name: akitchensyncio
Version: 0.1.1
Summary: Utility functions for asyncio which Stephan wished where in the stdlib but aren't.
Home-page: https://github.com/stephanh42/akitchensyncio
Author: Stephan Houben
Author-email: stephanh42@gmail.com
License: MIT
Keywords: asyncio
Platform: UNKNOWN
Classifier: Development Status :: 3 - Alpha
Classifier: Intended Audience :: Developers
Classifier: Topic :: Software Development :: Build Tools
Classifier: License :: OSI Approved :: MIT License
Classifier: Programming Language :: Python :: 3
Classifier: Programming Language :: Python :: 3.5
Classifier: Programming Language :: Python :: 3.6
Requires-Python: ~=3.5
Provides-Extra: dev
Provides-Extra: test
